abnorm/__init__.py
abnorm/contrib.py
abnorm/fields.py
abnorm/models.py
abnorm/state.py
abnorm/utils.py
abnorm/adapters/__init__.py
abnorm/adapters/base.py
abnorm/adapters/django2p2.py
abnorm/adapters/django3p0.py
abnorm/adapters/django3p1.py
abnorm/adapters/django3p2.py
abnorm/adapters/django4p0.py
abnorm/adapters/django4p1.py
abnorm/adapters/django4p2.py
abnorm/management/__init__.py
abnorm/management/commands/__init__.py
abnorm/management/commands/update_abnorm_fields.py
abnorm_tests/__init__.py
abnorm_tests/manage.py
abnorm_tests/settings.py
abnorm_tests/urls.py
abnorm_tests/tests/__init__.py
abnorm_tests/tests/models.py
abnorm_tests/tests/test_adapters.py
abnorm_tests/tests/test_commands.py
abnorm_tests/tests/test_fields.py
abnorm_tests/tests/migrations/0001_initial.py
abnorm_tests/tests/migrations/__init__.py
django_abnorm-1.4.0.dist-info/LICENSE
django_abnorm-1.4.0.dist-info/METADATA
django_abnorm-1.4.0.dist-info/WHEEL
django_abnorm-1.4.0.dist-info/top_level.txt
django_abnorm-1.4.0.dist-info/RECORD
